[
  {
      "text": "Лучшие сны происходят, когда вы бодрствуете.",
      "author": "Черри Гилдерблум"
  },
  {
      "text": "Успех — это умение двигаться от неудачи к неудаче, не теряя энтузиазма.",
      "author": "Уинстон Черчилль"
  },
  {
      "text": "Воплощайте собственные мечты, или кто-то другой наймёт вас, чтобы воплощать свои.",
      "author": "Фаррах Грей"
  },
  {
      "text": "Наша жизнь есть то, что мы думаем о ней.",
      "author": "М. Аврелий"
  },
  {
      "text": "Успех — это один процент вдохновения и девяносто девять процентов пота.",
      "author": "Томас Эдисон"
  },
  {
      "text": "Вы живете только один раз, но если вы все делаете правильно, достаточно одного раза.",
      "author": "Мэй Уэст"
  },
  {
      "text": "Неудача – это просто возможность начать снова, но уже более мудро.",
      "author": "Генри Форд"
  },
  {
    "text": "Всегда выбирайте самый трудный путь - на нем вы не встретите конкурентов",
    "author": "Шарль де Голль"
  },
  {
      "text": "Делай все, что можешь, там, где ты находишься, используя все, что имеешь",
      "author": "Теодор Рузвельт"
  },
  {
      "text": "Думай как человек действия и действуй как человек мысли.",
      "author": "Анри Бергсон"
  },
  {
      "text": "Жизнь меряется не тем, сколько в ней лет, а тем, сколько в этих годах настоящей жизни",
      "author": "Авраам Линкольн"
  },
  {
      "text": "Две вещи бесконечны — Вселенная и человеческая глупость, но насчёт Вселенной я не уверен.",
      "author": "Альберт Эйнштейн"
  },
  {
      "text": "Успех — дитя смелости.",
      "author": "Бенджамин Дизраэли"
  },
  {
      "text": "Всегда прощайте своих врагов — ничто не раздражает их сильнее.",
      "author": "Оскар Уайльд"
  },
  {
      "text": "Успех — не ключ к счастью. Это счастье — ключ к успеху.",
      "author": "Герман Кейн"
  },
  {
      "text": "Мы не помним дни, мы помним моменты.",
      "author": "Че́заре Паве́зе"
  }
]
